pybithumb/__init__.py
pybithumb/client.py
pybithumb/core.py
pybithumb/history.py
pybithumb/util.py
pybithumb/websocket.py
pybithumb-1.0.20.dist-info/LICENSE
pybithumb-1.0.20.dist-info/METADATA
pybithumb-1.0.20.dist-info/WHEEL
pybithumb-1.0.20.dist-info/top_level.txt
pybithumb-1.0.20.dist-info/RECORD
